gav_quantum/__init__.py
gav_quantum/core.py
gav_quantum-0.0.8.dist-info/licenses/LICENSE
gav_quantum-0.0.8.dist-info/METADATA
gav_quantum-0.0.8.dist-info/WHEEL
gav_quantum-0.0.8.dist-info/top_level.txt
gav_quantum-0.0.8.dist-info/RECORD
