Metadata-Version: 2.4
Name: gav_quantum
Version: 0.0.8
Summary: A quantum information utility package.
Author-email: Emil Marinov <emil@intp.io>
License-Expression: MIT
Project-URL: Homepage, https://github.com/grayalienventures/gav_quantum
Project-URL: Issues, https://github.com/grayalienventures/gav_quantum/issues
Classifier: Programming Language :: Python :: 3
Classifier: Operating System :: OS Independent
Classifier: Topic :: Scientific/Engineering
Classifier: Topic :: Scientific/Engineering :: Quantum Computing
Classifier: Topic :: Scientific/Engineering :: Physics
Classifier: Topic :: Scientific/Engineering :: Mathematics
Requires-Python: >=3.9
License-File: LICENSE
Dynamic: license-file
